player_tools_dsl_generator/__init__.py
player_tools_dsl_generator/__main__.py
player_tools_dsl_generator/generator.py
player_tools_dsl_generator/utils.py
player_tools_dsl_generator-0.13.0.dev2215853.dist-info/WHEEL
player_tools_dsl_generator-0.13.0.dev2215853.dist-info/METADATA
player_tools_dsl_generator-0.13.0.dev2215853.dist-info/RECORD
