Metadata-Version: 2.1
Name: player_tools_dsl_generator
Requires-Dist: player_tools_xlr_types==0.13.0dev2215853
Version: 0.13.0.dev2215853
